LICENSE
README.md
setup.py
git_assistente/__init__.py
git_assistente/__main__.py
git_assistente.egg-info/PKG-INFO
git_assistente.egg-info/SOURCES.txt
git_assistente.egg-info/dependency_links.txt
git_assistente.egg-info/entry_points.txt
git_assistente.egg-info/requires.txt
git_assistente.egg-info/top_level.txt
git_assistente/core/__init__.py
git_assistente/core/check_reponse.py
git_assistente/core/clear.py
git_assistente/core/cmd.py
git_assistente/core/get_repository_name.py
git_assistente/core/typewriter.py
git_assistente/utils/__init__.py
git_assistente/utils/banner.py