Metadata-Version: 2.1
Name: git-assistente
Version: 0.0.9
Summary: Um assistente do Git para subir projetos no GitHub
Home-page: UNKNOWN
Author: CarlosAllberto
Author-email: dasilvacarlosalberto344@gmail.com
License: MIT License
Keywords: git assistente
Platform: UNKNOWN
License-File: LICENSE
